easypheno/__init__.py
easypheno/optim_pipeline.py
easypheno/run.py
easypheno/evaluation/__init__.py
easypheno/evaluation/eval_metrics.py
easypheno/model/__init__.py
easypheno/model/_base_model.py
easypheno/model/_bayesfromR.py
easypheno/model/_bayesian_linreg.py
easypheno/model/_model_functions.py
easypheno/model/_param_free_base_model.py
easypheno/model/_sklearn_model.py
easypheno/model/_template_sklearn_model.py
easypheno/model/_template_tensorflow_model.py
easypheno/model/_template_torch_model.py
easypheno/model/_tensorflow_model.py
easypheno/model/_torch_model.py
easypheno/model/bayesAfromR.py
easypheno/model/bayesBfromR.py
easypheno/model/bayesCfromR.py
easypheno/model/bayes_ridge.py
easypheno/model/blup.py
easypheno/model/cnn.py
easypheno/model/elasticnet.py
easypheno/model/linearregression.py
easypheno/model/localcnn.py
easypheno/model/mlp.py
easypheno/model/randomforest.py
easypheno/model/svm.py
easypheno/model/xgboost.py
easypheno/optimization/__init__.py
easypheno/optimization/optuna_optim.py
easypheno/optimization/paramfree_fitting.py
easypheno/postprocess/__init__.py
easypheno/postprocess/feat_importance.py
easypheno/postprocess/model_reuse.py
easypheno/postprocess/rerun_inference.py
easypheno/postprocess/results_analysis.py
easypheno/postprocess/run_inference.py
easypheno/postprocess/run_plot_results.py
easypheno/postprocess/run_post_generate_feat_impo.py
easypheno/postprocess/run_retrain_on_new_data.py
easypheno/postprocess/run_summarize_results.py
easypheno/preprocess/__init__.py
easypheno/preprocess/base_dataset.py
easypheno/preprocess/encoding_functions.py
easypheno/preprocess/raw_data_functions.py
easypheno/simulate/__init__.py
easypheno/simulate/results_analysis_synthetic_data.py
easypheno/simulate/run_results_analysis_synthetic_data.py
easypheno/simulate/run_synthetic_phenotypes.py
easypheno/simulate/synthetic_phenotypes.py
easypheno/utils/__init__.py
easypheno/utils/check_functions.py
easypheno/utils/helper_functions.py
easypheno-0.0.5.dist-info/LICENSE
easypheno-0.0.5.dist-info/METADATA
easypheno-0.0.5.dist-info/WHEEL
easypheno-0.0.5.dist-info/top_level.txt
easypheno-0.0.5.dist-info/RECORD
