Metadata-Version: 2.1
Name: easypheno
Version: 0.0.5
Summary: state-of-the-art and easy-to-use plant phenotype prediction
Home-page: https://github.com/grimmlab/easyPheno
Author: Florian Haselbeck, Maura John, Dominik G. Grimm
License: GPLv3
Project-URL: Documentation, https://easypheno.readthedocs.io/
Project-URL: Source, https://github.com/grimmlab/easyPheno
Classifier: Development Status :: 4 - Beta
Classifier: Intended Audience :: Science/Research
Classifier: License :: OSI Approved :: GNU General Public License v3 (GPLv3)
Classifier: Operating System :: POSIX :: Linux
Classifier: Programming Language :: Python :: 3
Classifier: Topic :: Scientific/Engineering :: Bio-Informatics
Requires-Python: >=3.8
License-File: LICENSE
Requires-Dist: torch (>=1.11.0)
Requires-Dist: xgboost (>=1.5.2)
Requires-Dist: optuna (==2.10.0)
Requires-Dist: joblib (>=1.1.0)
Requires-Dist: numpy (>=1.22.2)
Requires-Dist: pandas (>=1.4.1)
Requires-Dist: pandas-plink (>=2.2.9)
Requires-Dist: h5py (>=3.5.0)
Requires-Dist: scikit-learn (>=1.0.2)
Requires-Dist: tensorflow (>=2.8.0)
Requires-Dist: XlsxWriter (>=3.0.3)
Requires-Dist: seaborn (>=0.11.2)
Requires-Dist: pyro-ppl (>=1.8.1)
